setup.py
distributions_testuno/Binomialdistribution.py
distributions_testuno/Gaussiandistribution.py
distributions_testuno/Generaldistribution.py
distributions_testuno/__init__.py
distributions_testuno.egg-info/PKG-INFO
distributions_testuno.egg-info/SOURCES.txt
distributions_testuno.egg-info/dependency_links.txt
distributions_testuno.egg-info/not-zip-safe
distributions_testuno.egg-info/top_level.txt